awsjsondataset/__init__.py
awsjsondataset/_version.py
awsjsondataset/constants.py
awsjsondataset/exceptions.py
awsjsondataset/models.py
awsjsondataset/types.py
awsjsondataset/utils.py
awsjsondataset/services/__init__.py
awsjsondataset/services/models.py
awsjsondataset/services/utils.py
aws_json_dataset-0.1.0.dist-info/LICENSE
aws_json_dataset-0.1.0.dist-info/METADATA
aws_json_dataset-0.1.0.dist-info/WHEEL
aws_json_dataset-0.1.0.dist-info/top_level.txt
aws_json_dataset-0.1.0.dist-info/RECORD
