Metadata-Version: 2.1
Name: aws-json-dataset
Version: 0.1.0
Summary: Send JSON datasets to various AWS services.
Author-email: Gregory Lindsey <gclindsey@gmail.com>
License: MIT License
Keywords: aws,json,dataset,s3,kinesis,firehose,sqs,data,streaming,data engineering
Classifier: Development Status :: 3 - Alpha
Classifier: License :: OSI Approved :: MIT License
Classifier: Operating System :: OS Independent
Classifier: Programming Language :: Python :: 3.10
Classifier: Topic :: Software Development :: Libraries :: Python Modules
Classifier: Topic :: Utilities
Classifier: Topic :: File Formats :: JSON
Requires-Python: >=3.10
License-File: LICENSE
Requires-Dist: boto3 >=1.20
Provides-Extra: dev
Requires-Dist: black >=21.12 ; extra == 'dev'
Provides-Extra: test
Requires-Dist: pytest >=6.2 ; extra == 'test'
Requires-Dist: pytest-cov >=3.0 ; extra == 'test'
Requires-Dist: coverage >=6.0 ; extra == 'test'
Requires-Dist: black >=21.12 ; extra == 'test'
Requires-Dist: boto3 >=1.20 ; extra == 'test'
Requires-Dist: moto[firehose,s3,sns,sqs,sts] >=2.2 ; extra == 'test'
